iConsol.cp37-win_amd64.pyd
pyConsol.cp37-win_amd64.pyd
pyConsol-1.0.6.dist-info/LICENSE
pyConsol-1.0.6.dist-info/METADATA
pyConsol-1.0.6.dist-info/WHEEL
pyConsol-1.0.6.dist-info/top_level.txt
pyConsol-1.0.6.dist-info/RECORD
