Metadata-Version: 2.1
Name: pyConsol
Version: 1.0.6
Summary: Python implementation of iConsol program for computing nonlinear consolidation of soil.
Home-page: UNKNOWN
Author: Scott J. Brandenberg
Author-email: sjbrandenberg@ucla.edu
License: UNKNOWN
Platform: UNKNOWN
